setup.py
baokaifang.egg-info/PKG-INFO
baokaifang.egg-info/SOURCES.txt
baokaifang.egg-info/dependency_links.txt
baokaifang.egg-info/top_level.txt
bkf/bkf.py