Metadata-Version: 1.0
Name: baokaifang
Version: 0.0.1
Summary: personal packages
Home-page: UNKNOWN
Author: bkf
Author-email: 736781877@qq.com
License: UNKNOWN
Platform: UNKNOWN
